Metadata-Version: 2.1
Name: odoo12-addon-sale_invoice_policy
Version: 12.0.1.0.1
Summary: Sales Management: let the user choose the invoice policy on the order
Home-page: https://github.com/OCA/sale-workflow
Author: ACSONE SA/NV, Odoo Community Association (OCA)
Author-email: support@odoo-community.org
License: AGPL-3
Classifier: Programming Language :: Python
Classifier: Framework :: Odoo
Classifier: Framework :: Odoo :: 12.0
Classifier: License :: OSI Approved :: GNU Affero General Public License v3
Requires-Python: >=3.5
Requires-Dist: odoo<12.1dev,>=12.0a
